yiriob/adapters/__init__.py
yiriob/adapters/base.py
yiriob/adapters/reverse_websocket.py
yiriob/bot.py
yiriob/event/__init__.py
yiriob/event/base.py
yiriob/event/bus.py
yiriob/event/events.py
yiriob/exceptions/__init__.py
yiriob/exceptions/api.py
yiriob/interface/__init__.py
yiriob/interface/base.py
yiriob/interface/message.py
yiriob/message/__init__.py
yiriob/message/message_chain.py
yiriob/message/message_components.py
yiriob/utils/__init__.py
yiriob/utils/logger.py
yiri_onebot-0.0.1b1.dist-info/LICENSE.md
yiri_onebot-0.0.1b1.dist-info/METADATA
yiri_onebot-0.0.1b1.dist-info/WHEEL
yiri_onebot-0.0.1b1.dist-info/RECORD
