Metadata-Version: 2.1
Name: yiri-onebot
Version: 0.0.1b1
Summary: YiriOneBot 是一个低耦合、异步的高性能OneBot 11 SDK。
Home-page: https://github.com/YiriMiraiProject/YiriOneBot
License: LGPL-3.0
Author: XYCode Kerman
Author-email: xycode-xyc@outlook.com
Requires-Python: >=3.10,<3.13
Classifier: Development Status :: 3 - Alpha
Classifier: Framework :: AsyncIO
Classifier: Intended Audience :: Developers
Classifier: License :: OSI Approved :: GNU Lesser General Public License v3 (LGPLv3)
Classifier: Programming Language :: Python :: 3
Classifier: Programming Language :: Python :: 3.10
Classifier: Programming Language :: Python :: 3.11
Classifier: Programming Language :: Python :: 3.12
Classifier: Programming Language :: Python :: 3 :: Only
Classifier: Programming Language :: Python :: 3.13
Classifier: Programming Language :: Python :: 3.14
Classifier: Topic :: Communications
Requires-Dist: pydantic (>=2.8.2,<3.0.0)
Requires-Dist: rich (>=13.7.1,<14.0.0)
Requires-Dist: websockets (>=12.0,<13.0)
Project-URL: Repository, https://github.com/YiriMiraiProject/YiriOneBot
